dover/__init__.py
dover/__main__.py
dover/cli.py
dover/commands.py
dover/format.py
dover/parse.py
dover/project.py
dover/util.py
dover/version.py
dover-0.5.1.dist-info/DESCRIPTION.rst
dover-0.5.1.dist-info/LICENSE.txt
dover-0.5.1.dist-info/METADATA
dover-0.5.1.dist-info/RECORD
dover-0.5.1.dist-info/WHEEL
dover-0.5.1.dist-info/entry_points.txt
dover-0.5.1.dist-info/metadata.json
dover-0.5.1.dist-info/top_level.txt
