Metadata-Version: 2.0
Name: dover
Version: 0.5.1
Summary: A tool for tracking and incrementing project version numbering.
Home-page: https://bitbucket.org/mgemmill/dover
Author: Mark Gemmill
Author-email: dev@markgemmill.com
License: BSD License
Keywords: project version versioning dover
Platform: UNKNOWN
Classifier: Development Status :: 4 - Beta
Classifier: Intended Audience :: Developers
Classifier: License :: OSI Approved :: BSD License
Classifier: Natural Language :: English
Classifier: Programming Language :: Python :: 3.6
Classifier: Programming Language :: Python :: 3.7
Requires-Dist: docopt
Requires-Dist: toml
